{"version":1,"resource":"file:///d%3A/Univer%20%28labs%29/AD%20Python/LR8/main.py","entries":[{"id":"rsAl.py","timestamp":1700655147141},{"id":"2m4E.py","timestamp":1700655196680},{"id":"wWpc.py","timestamp":1700655217593},{"id":"qeV2.py","timestamp":1700655228269},{"id":"gGmD.py","timestamp":1700655286260},{"id":"tnBf.py","source":"undoRedo.source","timestamp":1700655297826},{"id":"fCHj.py","timestamp":1700655306506},{"id":"hkvi.py","timestamp":1700655354347},{"id":"roaW.py","timestamp":1700655370797},{"id":"WrNE.py","timestamp":1700655384729},{"id":"fe9O.py","source":"undoRedo.source","timestamp":1700655413519},{"id":"h2eN.py","timestamp":1700655446558},{"id":"Hv4P.py","source":"undoRedo.source","timestamp":1700655478387},{"id":"FK2i.py","timestamp":1700655519197},{"id":"z5dT.py","timestamp":1700655543057},{"id":"1IyL.py","timestamp":1700655605264},{"id":"WJhV.py","source":"undoRedo.source","timestamp":1700655609626},{"id":"K5vp.py","timestamp":1700655620083},{"id":"RTAr.py","source":"undoRedo.source","timestamp":1700655623989},{"id":"zhLf.py","source":"undoRedo.source","timestamp":1700655661835},{"id":"U6lN.py","timestamp":1700655805273},{"id":"9ejy.py","timestamp":1700655839288},{"id":"wvBJ.py","source":"undoRedo.source","timestamp":1700655920978},{"id":"FUhb.py","timestamp":1700656065328},{"id":"JiMO.py","timestamp":1700656075887},{"id":"YM9j.py","timestamp":1700656092722},{"id":"z2bJ.py","timestamp":1700656115040},{"id":"EXcP.py","timestamp":1700656149728},{"id":"GNcp.py","source":"undoRedo.source","timestamp":1700656389931},{"id":"r6VB.py","timestamp":1700656492290},{"id":"djEx.py","timestamp":1700656592439},{"id":"OzJF.py","timestamp":1700656604943},{"id":"5bY9.py","timestamp":1700656647151},{"id":"UulJ.py","timestamp":1700656694536},{"id":"f0qx.py","timestamp":1700657026039},{"id":"s9Ls.py","timestamp":1700659884740},{"id":"jg72.py","timestamp":1700659905473},{"id":"2yBJ.py","source":"undoRedo.source","timestamp":1700660021635},{"id":"8EnJ.py","source":"undoRedo.source","timestamp":1700660065226},{"id":"etnU.py","timestamp":1700660081267},{"id":"yOef.py","timestamp":1700660093242},{"id":"YOG9.py","timestamp":1700660117037},{"id":"sNie.py","source":"undoRedo.source","timestamp":1700660152680},{"id":"kTdK.py","timestamp":1700660303503},{"id":"RRLN.py","timestamp":1700662017903},{"id":"9lZu.py","timestamp":1700662033550},{"id":"tdrg.py","timestamp":1700662044422},{"id":"YBlt.py","timestamp":1700662066973},{"id":"SEXb.py","source":"undoRedo.source","timestamp":1700662095174},{"id":"EdmP.py","timestamp":1700663170161}]}